[
{
"K4U6E3S4AA-MGCL":"AA-MGCL",
"K4U6E3S4AM-MGCJ":"AM-MGCJ",
"K4U6E3S4AB-MGCL":"AB-MGCL",
"K4FBE3S4HM-MGXX":"HM-MGXX",
"K4F6E304HB-MGCH":"HB-MGCH",
"K4UBE3D4AA-MGCL":"AA-MGCL 8GB",
"K4UBE3D4AM-MGCJ":"AM-MGCJ 8GB",
"K4U6E3D4AB-MGCL":"AB-MGCL 8GB",
"K4FBE3D4HM-MGXX":"HM-MGXX 8GB",
"K4F6E305HB-MGCH":"HB-MGCH 8GB",

"MT53E512M32D2NP-046 WT:F":"WT:F",
"MT53E512M32D2NP-046 WT:E":"WT:E",
"MT53E512M32D1NP-046 WT:B":"WT:B",
"MT53B512M32D2NP-062 WT:C":"WT:C",
"MT53E512M32D1ZW-046 AUT:B":"AUT:B",
"MT53E512M32D3NP-046 WT:F":"WT:F 8GB",
"MT53E512M32D3NP-046 WT:E":"WT:E 8GB",
"MT53E512M32D2NP-046 WT:B":"WT:B 8GB",
"MT53B512M32D3NP-046 WT:C":"WT:C 8GB",
"MT53E512M32D2ZW-046 AUT:B":"AUT:B 8GB",

"H9HCNNNBKMMLHR-NME":"NME",
"H9HCNNNBKMMLXR-NEE":"NEE",
"H9HCNNNBPUMLHR-NLE":"NLE",
"H9HCNNNBKMMLXR-NEI":"NEI",
"H9HCNNNBKMMLLR-NME":"NME 8GB",
"H9HCNNNBKMMLLR-NEE":"NEE 8GB",
"H9HCNNNBPUMLLR-NLE":"NLE 8GB",
"H9HCNNNBPUMLLR-NEI":"NEI 8GB"
}
]